pyworkshop/__init__.py
pyworkshop/module_one.py
pyworkshop-0.0.2.dist-info/LICENSE
pyworkshop-0.0.2.dist-info/METADATA
pyworkshop-0.0.2.dist-info/WHEEL
pyworkshop-0.0.2.dist-info/top_level.txt
pyworkshop-0.0.2.dist-info/RECORD
