Metadata-Version: 2.1
Name: pyworkshop
Version: 0.0.2
Summary: A python worskhop package
Home-page: https://github.com/yForecasting/pyworkshop
Author: Yves R. Sagaert
Author-email: yves.r.sagaert@pm.me
License: GNU GPLv3
Project-URL: Bug Tracker, https://github.com/yForecasting/pyworkshop/issues
Platform: UNKNOWN
Classifier: Programming Language :: Python :: 3
Classifier: License :: OSI Approved :: GNU General Public License v3 (GPLv3)
Classifier: Operating System :: OS Independent
Requires-Python: >=3.6
License-File: LICENSE
Requires-Dist: numpy
